egrep/__init__.py
egrep/egrep.py
egrep-0.0.1.dist-info/LICENSE
egrep-0.0.1.dist-info/METADATA
egrep-0.0.1.dist-info/WHEEL
egrep-0.0.1.dist-info/top_level.txt
egrep-0.0.1.dist-info/RECORD
