Metadata-Version: 2.1
Name: egrep
Version: 0.0.1
Summary: A simple library for exectuing egrep linux commando to files
Home-page: https://github.com/rhimmelbauer/egrep
Author: Roberto Himmelbauer
Author-email: robertoh89@gmail.com
License: UNKNOWN
Platform: UNKNOWN
Classifier: Programming Language :: Python :: 3
Classifier: License :: OSI Approved :: MIT License
Classifier: Operating System :: OS Independent
Requires-Python: >=python3.7
